{
  "name": "Annie Flores",
  "age": 41,
  "address": {
    "street": "Nufsi Boulevard",
    "city": "Dorafad",
    "state": "MD",
    "zip": "07987"
  },
  "contact": {
    "phone": "(403) 999-8210",
    "servicePhone": "800547969"
  },
  "birthday": "1974-09-01T16:36:17.922Z",
  "ip": "109.151.142.230",
  "foo": "bar",
  "profile": {
    "about": "Lobvak kefon tuci zolunpin gacwitad bida calik efihi lovta numbej winbupmir na jonisho sif. Feetanul afujenta ekiheh zi tiso mujda tojfokuw uposo gilhumi ecedu docovec wivrez wiuk tahzuz na. Vib teguk buz av obu jesiena majva kuneg uvpisif ju no fewobta lujligez alainipab ameasuseg cawdaneva. Humhot ifurino dudengo we no go of sefviwoh cuabnu ki mokpis gafum biesob. Wotaz povug buw cac puson lare un puj joaw wavan ah ignupi zed. Jogit ul tetakbi satgo nu ihtowsu fuzagin gulbub duve lefib lit va liduw ikohur.",
    "bio": "Wokfom ovimaina nida ro bof za funigse pomiz jocwodut necbolu nivhez hu ukac. Sotnofhiv onanarlu ennob fisnisvel wujnipigi ihifafe nepkutub wumzesti wi kig gonmat ka safuk gigwe. Ha zec puzu ro meag ara let hormadok oredif suive jip tu nikobwi wu jodnew jokavmov. Iwa si aj rostoka rof vekehgo ruw uhovawsip zerfaugu osogo niac pepoci atadejmu natgilab. Fat ne lomvulac cefnuhi juwuvi sidoned mosdu nokjajag vog ge urcezze tugem nihfov sotez opetusis bu. Emauda rusar obtaz vamnan ojno zi nip kimbugkad zafebo giafi negazi jurahu catu cer."
  },
  "apiKey": "b0160a626ceca1da7b0aad42ad486d8562d62ad72f1a540f656e0fdf409deac8",
  "currency": {
    "code": "PEN",
    "name": "Peru Nuevo Sol"
  }
}