{
  "name": "Lillian Lyons",
  "age": 34,
  "address": {
    "street": "Dugon Highway",
    "city": "Lemebpiz",
    "state": "KS",
    "zip": "44013"
  },
  "contact": {
    "phone": "(645) 578-1825",
    "servicePhone": "800711574"
  },
  "birthday": "1987-08-07T13:12:58.557Z",
  "ip": "219.248.40.166",
  "foo": "bar",
  "profile": {
    "about": "Ij ho bus zagwik emuru cohdaf loojte ofwoh tuh ha cuf utileg gop dogijbi sid. Botma wenuzen uvu ova sil hoehu coflek sovpihjub wij rolorer nuc ke. Po vo mepuwi cewdeci kaecle vipufehun ri im tifa poheza puhona mav ra uwafomjog enenilzej cozi tanron tucicla. Ukigi joweew socidom ce tac bopagve seorim bepak ickito pane mursok popazki liis bubruw. Lehevopin wughotos pug galiwoti vi ku upu obi red bolvu anosaran ih fokit res cut fid. Jez mudwid mitti sujfe pugasaw saucub joneto sokdu wek ep ok ipsa riji repabeb. Usdi tot larek ophobut durulbez nugira vig opsijkeg rig subopo vacec ifatu nowitdu livtogu.",
    "bio": "Raek pohi geze se poz cunbetjer bogor caupadur ciacu usuki lukdigko mesowak di cubic oc. Ledmuhip sepusu logavu adla gilpowog pikfub tesovbi dupi one lu aduwije duev itu wi pa. Givafi nizi da ejeput tasgidnem dehle ci ceal pamipipe ejdi cafkirpuj biketoza no geghu gowidoeju."
  },
  "apiKey": "cc7e1dc1399db047f3a688fc839a3eb9635078c0ad674fff59bab165d7d482f4",
  "currency": {
    "code": "PLN",
    "name": "Poland Zloty"
  }
}