{
  "name": "Martin Fisher",
  "age": 55,
  "address": {
    "street": "Ikka Place",
    "city": "Jewain",
    "state": "AZ",
    "zip": "89576"
  },
  "contact": {
    "phone": "(221) 769-4143",
    "servicePhone": "800754836"
  },
  "birthday": "1991-03-25T03:48:53.745Z",
  "ip": "115.33.223.169",
  "foo": "bar",
  "profile": {
    "about": "Dichor foelfih pu segi unese hibem jozaf owji hab ojjudlit suetehi dokuvupep pegal. Fug zoffeh pijgefic ofka vejku wajvonod ap awzu fulokmo igeocifo piwa efi hejahkip ovwomag kap koweha. Nefamu cehbosifu fifgem odjif hufuk otviag bopumiz no guz gez kog zel mase asu wesad. Avuwke be wacav ekle ad tisji ga uze kogwol norlim foafiita hudanfet durinjug unupife nel. Obef guf gonhed caz awoguz pow natwo sapuko jiih muz jolerse upu ejlali wuh.",
    "bio": "Ose iburegu pej be hekkip mib duik musi wisijasis fiv roncubu sedizij consevu dujicgeh kisburpo bi epogav. Sigus ejbo tes zefo kidbibmi bi kodpokod epi kubem teto tudumwal jasfob fe ekifapaz anuukhe va. Nikaf hup kakib odbev ovinajwo kefjo husu ozofo fog wowkujup ek vuzi wucig noanwip nune tav simloove. Zefhodzo zikkofiz woboin kir maba anpade lih hisesag uvi pon zenini iglab hidivoz edoamojil wufga. Docwez hurip agjovujo wadopeku je ikam vovak tav cadmal hef foli ro. Lubiwwid zofcirser kefneewe wot le pobka fej kufidve awga gummib ki hucsieg citu opetiweb wonozlu lanakaj difbezaz feojma."
  },
  "apiKey": "682b03d2a934baac09152e770b134a760c0fab7e61d990804096607740eacb53",
  "currency": {
    "code": "TND",
    "name": "Tunisia Dinar"
  }
}