{
  "name": "Inez Obrien",
  "age": 32,
  "address": {
    "street": "Ilupo Junction",
    "city": "Hunrocso",
    "state": "CO",
    "zip": "27222"
  },
  "contact": {
    "phone": "(889) 732-5758",
    "servicePhone": "800136386"
  },
  "birthday": "1995-07-31T06:27:06.570Z",
  "ip": "239.166.197.30",
  "foo": "bar",
  "profile": {
    "about": "Uru sohut iborona nuimo zurta tohaj te vo zipsutig ihouzaok zumeiba egpeku. Reapotu bek hugno dic kero vidi ofinam pos uk lojda elvire horjaw. Ha joc so ebmevebi jus evsiku der adit bij be vopifuk peseb giumki zedhu debekwam nolfi fo nippaito. Redmaiw hezubma azi kugvobu mi aknebez lijlamivu gig avaboljan pone eca isdoj so fichoc azural. Ritwew ficuso ketwodin narvev tecopace en mob daof foaroeb ci owuve uduejki hawaoc efati gejomjov zep copu cac.",
    "bio": "Tazuc wusev ac tomih latim dodhawe bi vuhowpu hofaki eba amoke nir etoza tosda su fuso jek. Ow juvetoz jiub ri ofkawu dep cijcegbu enizodor hoten kube por zoc tu keal. Obinaze cefusuh bate ov fi gam mumucwoh anketuh ocoku mejanel pouka suwsanu rerpu tiserujem ka fo. Duufawat jilo dummibe ciwupza vupicwiw basowor poknuga surkej dabpoz gimnofif uti abajis wenuc zap ewocibfuv kubufmon nibuku. Navnitij cujfo kawa uriharit hu kagowaje gu isipoer deihse zuk meogves inkuv rumosfa su mugbagva ipozuaha hariliw. Legam ojigim wunol tubobfav vo ul sil jehaw urma lumme zecagju ac peregame."
  },
  "apiKey": "328ef5d58c3292db5de03f781e423556b687b738efbdcabfe385e4dee5748b6b",
  "currency": {
    "code": "GGP",
    "name": "Guernsey Pound"
  }
}